gpsmatcher/__init__.py
gpsmatcher/emission.py
gpsmatcher/gps.py
gpsmatcher/graph.py
gpsmatcher/map_matching.py
gpsmatcher/precomputation_emission.py
gpsmatcher/transition.py
gpsmatcher/utils.py
gpsmatcher-0.1.0.dist-info/LICENSE
gpsmatcher-0.1.0.dist-info/METADATA
gpsmatcher-0.1.0.dist-info/WHEEL
gpsmatcher-0.1.0.dist-info/top_level.txt
gpsmatcher-0.1.0.dist-info/RECORD
