Metadata-Version: 2.1
Name: gpsmatcher
Version: 0.1.0
Summary: Match a trace of GPS positions to a transportation graph
Author-email: Loïc Bonnetain <loic.bonnetain@univ-eiffel.fr>
License: GNU GENERAL PUBLIC LICENSE
Project-URL: Repository, https://github.com/lbonnetain/gpsmatcher.git
Project-URL: Issues, https://github.com/lbonnetain/gpsmatcher/issues
Keywords: map,matching,GPS,gpsmatcher
Classifier: Programming Language :: Python :: 3
Classifier: License :: OSI Approved :: GNU General Public License v3 (GPLv3)
Classifier: Operating System :: OS Independent
License-File: LICENSE
Requires-Dist: pandas
Requires-Dist: numpy
Requires-Dist: numba
Requires-Dist: networkx
Requires-Dist: geopandas
Requires-Dist: pygeohash-fast
Requires-Dist: joblib
Requires-Dist: scipy
